cptextract/__init__.py
cptextract/check_files.py
cptextract/load_files.py
cptextract/extract/__init__.py
cptextract/extract/agsfunctions.py
cptextract/extract/csvfunctions.py
cptextract/extract/excelfunctions.py
test/__init__.py
test/test_import.py
test/test_import_error.py
test/data/__init__.py
cptextract-0.1.1.dist-info/LICENSE
cptextract-0.1.1.dist-info/METADATA
cptextract-0.1.1.dist-info/WHEEL
cptextract-0.1.1.dist-info/top_level.txt
cptextract-0.1.1.dist-info/RECORD
