Metadata-Version: 2.1
Name: cptextract
Version: 0.1.1
Summary: A simple Python package to automate the extraction of CPT data
Home-page: https://github.com/geocodes-eng/cptextract
Author: geocoder-eng
License: UNKNOWN
Keywords: geotechnical,cpt
Platform: UNKNOWN
Classifier: Programming Language :: Python :: 3
Classifier: Development Status :: 3 - Alpha
Classifier: License :: OSI Approved :: MIT License
License-File: LICENSE
Requires-Dist: numpy
Requires-Dist: pandas
Requires-Dist: python-ags4
Requires-Dist: openpyxl
Requires-Dist: xlrd
Requires-Dist: pyexcel
